cloudwright_bigquery/__init__.py
cloudwright_bigquery-0.0.0.dist-info/METADATA
cloudwright_bigquery-0.0.0.dist-info/WHEEL
cloudwright_bigquery-0.0.0.dist-info/top_level.txt
cloudwright_bigquery-0.0.0.dist-info/RECORD
