Metadata-Version: 2.1
Name: cloudwright-bigquery
Version: 0.0.0
Summary: cloudwright_bigquery
Home-page: https://cloudwright.io
Author: cloudwright
Author-email: founders@cloudwright.io
License: UNKNOWN
Platform: UNKNOWN
Classifier: Programming Language :: Python :: 3
Classifier: Operating System :: OS Independent
